[
    {
        "break": false,
        "tags": [
            "one",
            "two"
        ],
        "countErrors": 22,
        "countRepeat": 41,
        "countSuccess": 19,
        "en": [
            "teach",
            "taught"
        ],
        "ru": [
            "учить"
        ],
        "id": "1aeaf26b-3591-4b9c-af15-5c2820af60dc"
    },
    {
        "break": false,
        "tags": [
            "one"
        ],
        "countErrors": 6,
        "countRepeat": 18,
        "countSuccess": 12,
        "en": [
            "think",
            "thought"
        ],
        "ru": [
            "думать"
        ],
        "id": "bb856b4e-45c7-429d-ab26-e3caa1248d89"
    },
    {
        "break": false,
        "tags": [
            "one"
        ],
        "countErrors": 6,
        "countRepeat": 20,
        "countSuccess": 14,
        "en": [
            "seek",
            "sought"
        ],
        "ru": [
            "искать"
        ],
        "id": "e2790615-1bb9-4fae-b1de-a3360f1ad81d"
    },
    {
        "break": false,
        "tags": [
            "one"
        ],
        "countErrors": 2,
        "countRepeat": 10,
        "countSuccess": 8,
        "en": [
            "catch",
            "caught"
        ],
        "ru": [
            "ловить"
        ],
        "id": "fb519591-c12d-402f-b389-b370da7fccce"
    },
    {
        "break": false,
        "tags": [
            "one",
            "two"
        ],
        "countErrors": 11,
        "countRepeat": 23,
        "countSuccess": 12,
        "en": [
            "bring",
            "bought"
        ],
        "ru": [
            "приносить"
        ],
        "id": "c9290f2d-c88c-46f0-b474-ce78bf0e5fe8"
    },
    {
        "break": false,
        "tags": [
            "one"
        ],
        "countErrors": 2,
        "countRepeat": 11,
        "countSuccess": 9,
        "en": [
            "buy",
            "bought"
        ],
        "ru": [
            "покупать"
        ],
        "id": "06a5f22d-9231-4e9e-a3e0-c13a0da2677f"
    },
    {
        "break": false,
        "tags": [
            "one"
        ],
        "countErrors": 0,
        "countRepeat": 3,
        "countSuccess": 3,
        "en": [
            "fight",
            "fought"
        ],
        "ru": [
            "бороться"
        ],
        "id": "6e53fd80-fe82-4aec-8362-a7814e036426"
    },
    {
        "break": false,
        "tags": [],
        "countErrors": 0,
        "countRepeat": 0,
        "countSuccess": 0,
        "en": [
            "bust"
        ],
        "ru": [
            "разрушать",
            "сломать"
        ],
        "id": "227ac0e7-a87e-4505-9d6f-5d7da41c6922"
    },
    {
        "break": false,
        "tags": [],
        "countErrors": 0,
        "countRepeat": 0,
        "countSuccess": 0,
        "en": [
            "cast"
        ],
        "ru": [
            "бросать",
            "кидать"
        ],
        "id": "33534180-e964-485e-83d2-7c2fc5174c09"
    },
    {
        "break": false,
        "tags": [
            "two"
        ],
        "countErrors": 0,
        "countRepeat": 0,
        "countSuccess": 0,
        "en": [
            "bleed",
            "bled"
        ],
        "ru": [
            "кровоточить"
        ],
        "id": "e25b08e2-f3c9-4be7-a5ef-9a7d6f5e18d7"
    },
    {
        "break": false,
        "tags": [
            "two"
        ],
        "countErrors": 5,
        "countRepeat": 8,
        "countSuccess": 3,
        "en": [
            "breed",
            "bred"
        ],
        "ru": [
            "воспитывать",
            "вынашивать"
        ],
        "id": "6e69c732-6d65-4f14-a13d-10b1abfd62c4"
    },
    {
        "break": false,
        "tags": [
            "two"
        ],
        "countErrors": 16,
        "countRepeat": 26,
        "countSuccess": 10,
        "en": [
            "creep",
            "crept"
        ],
        "ru": [
            "ползать"
        ],
        "id": "9cd86d7d-49b1-4c2c-aed5-b59bbce55914"
    },
    {
        "break": false,
        "tags": [
            "two"
        ],
        "countErrors": 2,
        "countRepeat": 4,
        "countSuccess": 2,
        "en": [
            "say",
            "said"
        ],
        "ru": [
            "говорить"
        ],
        "id": "0f0ad8ef-fd24-44b1-825c-70cc2797a3f8"
    },
    {
        "break": false,
        "tags": [
            "two"
        ],
        "countErrors": 0,
        "countRepeat": 2,
        "countSuccess": 2,
        "en": [
            "send",
            "sent"
        ],
        "ru": [
            "посылать"
        ],
        "id": "300de408-6499-4ad1-bf3b-bde20e3817d2"
    },
    {
        "break": false,
        "tags": [
            "two"
        ],
        "countErrors": 0,
        "countRepeat": 3,
        "countSuccess": 3,
        "en": [
            "speed",
            "sped"
        ],
        "ru": [
            "ускорять",
            "спешить"
        ],
        "id": "9d99d853-a29f-4dc7-b9cb-bf228712d1a8"
    },
    {
        "break": false,
        "tags": [
            "two"
        ],
        "countErrors": 2,
        "countRepeat": 3,
        "countSuccess": 1,
        "en": [
            "hew",
            "hewed"
        ],
        "ru": [
            "рубить"
        ],
        "id": "cfbdb43f-4328-4edd-9d19-fb00cd7fb133"
    },
    {
        "break": false,
        "tags": [
            "two"
        ],
        "countErrors": 4,
        "countRepeat": 6,
        "countSuccess": 2,
        "en": [
            "prove",
            "proved"
        ],
        "ru": [
            "доказывать"
        ],
        "id": "888d90ef-6bec-4df1-926d-24426e1c7fe0"
    },
    {
        "break": false,
        "tags": [
            "two"
        ],
        "countErrors": 0,
        "countRepeat": 0,
        "countSuccess": 0,
        "en": [
            "shake",
            "shook"
        ],
        "ru": [
            "встряхивать"
        ],
        "id": "930b5a27-de04-49e0-af51-38febfef4676"
    },
    {
        "break": false,
        "tags": [
            "two"
        ],
        "countErrors": 8,
        "countRepeat": 13,
        "countSuccess": 5,
        "en": [
            "shoe",
            "shod"
        ],
        "ru": [
            "обувать",
            "подковывать"
        ],
        "id": "a4c9697f-7ae5-4bc0-ab4a-b524613b1063"
    },
    {
        "break": false,
        "tags": [
            "two"
        ],
        "countErrors": 0,
        "countRepeat": 4,
        "countSuccess": 4,
        "en": [
            "shoot",
            "shot"
        ],
        "ru": [
            "стрелять"
        ],
        "id": "f32b5263-d286-4722-ba42-f290d40f56c1"
    },
    {
        "break": false,
        "tags": [
            "two"
        ],
        "countErrors": 3,
        "countRepeat": 7,
        "countSuccess": 4,
        "en": [
            "lose",
            "lost"
        ],
        "ru": [
            "терять"
        ],
        "id": "f4e6a875-d869-4c82-a5ae-10bc82d713c3"
    },
    {
        "break": false,
        "tags": [
            "two"
        ],
        "countErrors": 1,
        "countRepeat": 4,
        "countSuccess": 3,
        "en": [
            "spread"
        ],
        "ru": [
            "расстилать"
        ],
        "id": "e7519c5e-59cf-437f-95ae-df178b07e688"
    },
    {
        "break": false,
        "tags": [
            "two"
        ],
        "countErrors": 3,
        "countRepeat": 5,
        "countSuccess": 2,
        "en": [
            "abide",
            "abode"
        ],
        "ru": [
            "терпеть"
        ],
        "id": "b2343960-8b6e-4515-8231-67facdf90496"
    }
]